add_typing_final/__init__.py
add_typing_final/main.py
add_typing_final-0.1.0.dist-info/METADATA
add_typing_final-0.1.0.dist-info/WHEEL
add_typing_final-0.1.0.dist-info/entry_points.txt
add_typing_final-0.1.0.dist-info/licenses/LICENSE
add_typing_final-0.1.0.dist-info/RECORD
