Metadata-Version: 2.3
Name: add-typing-final
Version: 0.1.0
Project-URL: repository, https://github.com/vrslev/add-typing-final
Author-email: Lev Vereshchagin <mail@vrslev.com>
License: MIT
License-File: LICENSE
Keywords: automation,flake8,mypy,typing
Classifier: Development Status :: 4 - Beta
Classifier: Natural Language :: English
Classifier: Programming Language :: Python :: Implementation :: CPython
Classifier: Typing :: Typed
Requires-Python: >=3.12
Requires-Dist: ast-grep-py==0.24.0
